operaciones/__init__.py
operaciones/lib.py
libreria_Ander-0.1.0.dist-info/METADATA
libreria_Ander-0.1.0.dist-info/WHEEL
libreria_Ander-0.1.0.dist-info/top_level.txt
libreria_Ander-0.1.0.dist-info/RECORD
