Metadata-Version: 2.1
Name: libreria_Ander
Version: 0.1.0
Summary: La librería de Ander Oficial
Home-page: https://github.com/andercrispy/lib
Author: Ander
Author-email: tuemail@example.com
Classifier: Programming Language :: Python :: 3
Classifier: License :: OSI Approved :: MIT License
Classifier: Operating System :: OS Independent
Requires-Python: >=3.6
